{
  "hillId": "lakeside",
  "duration": 300,
  "breathCycle": { "inhale": 4, "exhale": 4 },
  "cues": [
    { "t": 0,   "text": "找一个舒服的姿势坐好，轻轻闭上眼睛。" },
    { "t": 20,  "text": "感受身体和座位接触的地方，让重量慢慢沉下去。" },
    { "t": 45,  "text": "注意你的呼吸。像湖水一样，一起，一伏。" },
    { "t": 90,  "text": "想象你的心是一片湖面，呼吸是吹过湖面的风。" },
    { "t": 150, "text": "情绪来了，像一圈涟漪。看着它升起，看着它散开。" },
    { "t": 210, "text": "波纹会平，湖面会静。你不需要做什么，水知道答案。" },
    { "t": 270, "text": "最后一次深呼吸。吸气……呼气……" },
    { "t": 292, "text": "准备好了，就慢慢睁开眼睛。" }
  ]
}
